{
  "backend": "coxiterCompactDiagramChecker",
  "backendVersion": "1.0.0",
  "coxiter": {
    "command": [
      "wsl",
      "-d",
      "Ubuntu-24.04",
      "--",
      "bash",
      "-lc",
      "coxiter < /mnt/c/Users/olu_o/AppData/Local/Temp/coxiter-graph-28dvshs4.coxiter"
    ],
    "exitCode": 0,
    "parsed": {
      "cocompact": "yes",
      "dimension": 5,
      "eulerCharacteristic": "0",
      "fVector": "14, 35, 40, 25, 8, 1",
      "finiteCovolume": "yes",
      "growthRate": "3.1046959886012131927230806474634512147",
      "signature": "6,2,0",
      "vertices": 8,
      "verticesAtInfinity": 0
    },
    "status": "passed",
    "stderr": "",
    "stdout": "Reading graph: \n\tNumber of vertices: 8\n\tDimension: 5\n\tVertices: t04_0, t04_1, t04_2, t04_3, t04_4, t04_5, t04_6, t04_7\n\tField generated by the entries of the Gram matrix: ?\nFile read\n\nFinding connected subgraphs......\nFinding graphs products......\nComputations......\n\tComputation time: 0.0870522s\n\nInformation\n\tCocompact: yes\n\tFinite covolume: yes\n\tf-vector: (14, 35, 40, 25, 8, 1)\n\tNumber of vertices at infinity: 0\n\tAlternating sum of the components of the f-vector: 2\n\tEuler characteristic: 0\n\tSignature (numerically): 6,2,0\n\nGrowth series: \nf(x) = C(2,2,2,2,2,3,3,4,4,5,5,6,6,10,10,12,15,20,30)/(1 - 3 * x - x^2 + 2 * x^3 + x^5 - x^7 + 2 * x^9 + x^10 - x^11 + x^12 + 2 * x^13 - x^14 + x^15 + x^16 - x^17 + 2 * x^18 + x^19 - x^20 + x^21 + 2 * x^22 - x^24 + x^26 + 2 * x^28 - x^29 - 2 * x^30 + 2 * x^31 + x^32 - 2 * x^33 - x^35 + x^37 - 2 * x^39 - x^40 + x^41 - x^42 - 2 * x^43 + x^44 - x^45 - x^46 + x^47 - 2 * x^48 - x^49 + x^50 - x^51 - 2 * x^52 + x^54 - x^56 - 2 * x^58 + x^59 + 3 * x^60 - x^61)\n\nGrowth rate: 3.1046959886012131927230806474634512147\n\tPerron number: yes\n\tPisot number: no\n\tSalem number: no"
  },
  "coxiterGraphSha256": "8d59feaad8e8a4ff0e23d55c67b52db18c859fa197b062e13056cca5d6c5c1c9",
  "inputFile": "public\\examples\\tumarkin_5d_8facet_g11411_04.json",
  "inputHash": "434573d6fe0a591be7f1910bb8e8cd97508cc48909cc10477bc9af00e402f026",
  "schemaVersion": 1
}
